{
  "generated_at": "2026-04-18T11:59:13.348788",
  "version": "3.103",
  "script_hash": "504417168730",
  "scan_hours": 72,
  "retention_days": 14,
  "activities": [
    {
      "activity_id": "i140742953",
      "date": "2026-04-18",
      "type": "Ride",
      "name": "Bunchie",
      "interval_summary": [
        "10x 40s 379w",
        "3x 61s 409w",
        "2x 81s 314w",
        "2x 56s 330w",
        "1x 2m45s 351w",
        "1x 12s 492w"
      ],
      "intervals": [
        {
          "type": "RECOVERY",
          "duration_secs": 556,
          "avg_power": 219,
          "max_power": 466,
          "avg_hr": 120,
          "max_hr": 134,
          "avg_cadence": 79.31654,
          "zone": 2,
          "training_load": 10.01323,
          "decoupling": 5.2651253
        },
        {
          "type": "WORK",
          "label": "40s@379w83rpm",
          "duration_secs": 43,
          "avg_power": 410,
          "max_power": 478,
          "avg_hr": 128,
          "max_hr": 135,
          "avg_cadence": 67.48837,
          "zone": 6,
          "training_load": 1.6499913,
          "decoupling": 5.9059143
        },
        {
          "type": "RECOVERY",
          "duration_secs": 55,
          "avg_power": 236,
          "max_power": 332,
          "avg_hr": 136,
          "max_hr": 137,
          "avg_cadence": 78.76363,
          "zone": 3,
          "training_load": 1.4591224,
          "decoupling": 1.7823391
        },
        {
          "type": "WORK",
          "label": "40s@379w83rpm",
          "duration_secs": 38,
          "avg_power": 332,
          "max_power": 376,
          "avg_hr": 136,
          "max_hr": 140,
          "avg_cadence": 71.947365,
          "zone": 5,
          "training_load": 1.0148306,
          "decoupling": 7.6405497
        },
        {
          "type": "RECOVERY",
          "duration_secs": 2499,
          "avg_power": 219,
          "max_power": 559,
          "avg_hr": 125,
          "max_hr": 142,
          "avg_cadence": 81.4226,
          "zone": 2,
          "training_load": 36.714203,
          "decoupling": -5.4445815
        },
        {
          "type": "WORK",
          "label": "61s@409w81rpm",
          "duration_secs": 57,
          "avg_power": 408,
          "max_power": 466,
          "avg_hr": 137,
          "max_hr": 146,
          "avg_cadence": 79.807014,
          "zone": 6,
          "training_load": 2.4483216,
          "decoupling": 8.183722
        },
        {
          "type": "RECOVERY",
          "duration_secs": 1517,
          "avg_power": 171,
          "max_power": 607,
          "avg_hr": 114,
          "max_hr": 148,
          "avg_cadence": 70.52208,
          "zone": 2,
          "training_load": 20.153053,
          "decoupling": 10.483278
        },
        {
          "type": "WORK",
          "label": "81s@314w81rpm",
          "duration_secs": 80,
          "avg_power": 302,
          "max_power": 387,
          "avg_hr": 121,
          "max_hr": 134,
          "avg_cadence": 73.375,
          "zone": 4,
          "training_load": 1.9565085,
          "decoupling": 18.36284
        },
        {
          "type": "RECOVERY",
          "duration_secs": 343,
          "avg_power": 131,
          "max_power": 528,
          "avg_hr": 103,
          "max_hr": 133,
          "avg_cadence": 53.51895,
          "zone": 1,
          "training_load": 3.7411473,
          "decoupling": 9.961038
        },
        {
          "type": "WORK",
          "label": "56s@330w84rpm",
          "duration_secs": 54,
          "avg_power": 326,
          "max_power": 379,
          "avg_hr": 118,
          "max_hr": 133,
          "avg_cadence": 79.5,
          "zone": 5,
          "training_load": 1.4041786,
          "decoupling": 10.29973
        },
        {
          "type": "RECOVERY",
          "duration_secs": 207,
          "avg_power": 233,
          "max_power": 436,
          "avg_hr": 125,
          "max_hr": 136,
          "avg_cadence": 79.797104,
          "zone": 3,
          "training_load": 4.129024,
          "decoupling": 24.588223
        },
        {
          "type": "WORK",
          "label": "40s@379w83rpm",
          "duration_secs": 39,
          "avg_power": 342,
          "max_power": 395,
          "avg_hr": 120,
          "max_hr": 131,
          "avg_cadence": 75.48718,
          "zone": 5,
          "training_load": 1.0693097,
          "decoupling": 3.4565187
        },
        {
          "type": "RECOVERY",
          "duration_secs": 821,
          "avg_power": 206,
          "max_power": 636,
          "avg_hr": 118,
          "max_hr": 136,
          "avg_cadence": 78.20585,
          "zone": 2,
          "training_load": 12.828125,
          "decoupling": -11.014195
        },
        {
          "type": "WORK",
          "label": "40s@379w83rpm",
          "duration_secs": 43,
          "avg_power": 383,
          "max_power": 452,
          "avg_hr": 132,
          "max_hr": 143,
          "avg_cadence": 90.46512,
          "zone": 6,
          "training_load": 1.5336115,
          "decoupling": 6.7755346
        },
        {
          "type": "RECOVERY",
          "duration_secs": 38,
          "avg_power": 237,
          "max_power": 326,
          "avg_hr": 141,
          "max_hr": 144,
          "avg_cadence": 92.23684,
          "zone": 3,
          "training_load": 1.0014336,
          "decoupling": -24.423996
        },
        {
          "type": "WORK",
          "label": "56s@330w84rpm",
          "duration_secs": 57,
          "avg_power": 334,
          "max_power": 447,
          "avg_hr": 139,
          "max_hr": 143,
          "avg_cadence": 88.57895,
          "zone": 5,
          "training_load": 1.6772177,
          "decoupling": -6.95462
        },
        {
          "type": "RECOVERY",
          "duration_secs": 447,
          "avg_power": 165,
          "max_power": 562,
          "avg_hr": 116,
          "max_hr": 144,
          "avg_cadence": 64.0962,
          "zone": 1,
          "training_load": 5.994199,
          "decoupling": 7.5914874
        },
        {
          "type": "WORK",
          "label": "81s@314w81rpm",
          "duration_secs": 82,
          "avg_power": 325,
          "max_power": 480,
          "avg_hr": 129,
          "max_hr": 139,
          "avg_cadence": 87.63415,
          "zone": 5,
          "training_load": 2.3223662,
          "decoupling": 14.837989
        },
        {
          "type": "RECOVERY",
          "duration_secs": 262,
          "avg_power": 126,
          "max_power": 446,
          "avg_hr": 106,
          "max_hr": 139,
          "avg_cadence": 59.282444,
          "zone": 1,
          "training_load": 2.5412076,
          "decoupling": -8.305502
        },
        {
          "type": "WORK",
          "label": "40s@379w83rpm",
          "duration_secs": 39,
          "avg_power": 375,
          "max_power": 436,
          "avg_hr": 119,
          "max_hr": 133,
          "avg_cadence": 80.92308,
          "zone": 6,
          "training_load": 1.228594,
          "decoupling": 18.188034
        },
        {
          "type": "RECOVERY",
          "duration_secs": 758,
          "avg_power": 196,
          "max_power": 551,
          "avg_hr": 114,
          "max_hr": 146,
          "avg_cadence": 54.82885,
          "zone": 2,
          "training_load": 9.142543,
          "decoupling": -16.188263
        },
        {
          "type": "WORK",
          "label": "61s@409w81rpm",
          "duration_secs": 62,
          "avg_power": 405,
          "max_power": 497,
          "avg_hr": 148,
          "max_hr": 151,
          "avg_cadence": 83.30645,
          "zone": 6,
          "training_load": 2.6909723,
          "decoupling": 3.3719754
        },
        {
          "type": "RECOVERY",
          "duration_secs": 378,
          "avg_power": 188,
          "max_power": 598,
          "avg_hr": 124,
          "max_hr": 151,
          "avg_cadence": 64.36141,
          "zone": 2,
          "training_load": 7.8922477,
          "decoupling": 9.132796
        },
        {
          "type": "WORK",
          "label": "40s@379w83rpm",
          "duration_secs": 35,
          "avg_power": 324,
          "max_power": 454,
          "avg_hr": 119,
          "max_hr": 128,
          "avg_cadence": 87.2,
          "zone": 5,
          "training_load": 0.8324417,
          "decoupling": 5.3597054
        },
        {
          "type": "RECOVERY",
          "duration_secs": 297,
          "avg_power": 187,
          "max_power": 559,
          "avg_hr": 118,
          "max_hr": 133,
          "avg_cadence": 61.420876,
          "zone": 2,
          "training_load": 4.8027306,
          "decoupling": -13.895629
        },
        {
          "type": "WORK",
          "label": "40s@379w83rpm",
          "duration_secs": 46,
          "avg_power": 375,
          "max_power": 421,
          "avg_hr": 139,
          "max_hr": 145,
          "avg_cadence": 88.28261,
          "zone": 6,
          "training_load": 1.7166839,
          "decoupling": 4.4934454
        },
        {
          "type": "RECOVERY",
          "duration_secs": 266,
          "avg_power": 161,
          "max_power": 509,
          "avg_hr": 117,
          "max_hr": 146,
          "avg_cadence": 61.834587,
          "zone": 1,
          "training_load": 4.3381214,
          "decoupling": -35.77875
        },
        {
          "type": "WORK",
          "label": "165s@351w81rpm",
          "duration_secs": 165,
          "avg_power": 351,
          "max_power": 414,
          "avg_hr": 142,
          "max_hr": 151,
          "avg_cadence": 81.27273,
          "zone": 5,
          "training_load": 5.7840524,
          "decoupling": 5.8097095
        },
        {
          "type": "RECOVERY",
          "duration_secs": 1,
          "avg_power": 325,
          "max_power": 325,
          "avg_hr": 150,
          "max_hr": 150,
          "avg_cadence": 88.0,
          "zone": 5,
          "training_load": 0.039010525
        },
        {
          "type": "WORK",
          "label": "61s@409w81rpm",
          "duration_secs": 65,
          "avg_power": 414,
          "max_power": 515,
          "avg_hr": 151,
          "max_hr": 153,
          "avg_cadence": 78.55385,
          "zone": 6,
          "training_load": 2.9846938,
          "decoupling": -5.8883176
        },
        {
          "type": "RECOVERY",
          "duration_secs": 351,
          "avg_power": 128,
          "max_power": 401,
          "avg_hr": 114,
          "max_hr": 153,
          "avg_cadence": 56.421654,
          "zone": 1,
          "training_load": 4.5758114,
          "decoupling": -26.408905
        },
        {
          "type": "WORK",
          "label": "40s@379w83rpm",
          "duration_secs": 39,
          "avg_power": 421,
          "max_power": 589,
          "avg_hr": 127,
          "max_hr": 141,
          "avg_cadence": 81.89744,
          "zone": 6,
          "training_load": 1.5381291,
          "decoupling": 2.0277975
        },
        {
          "type": "RECOVERY",
          "duration_secs": 195,
          "avg_power": 254,
          "max_power": 463,
          "avg_hr": 138,
          "max_hr": 146,
          "avg_cadence": 90.94359,
          "zone": 3,
          "training_load": 4.8352246,
          "decoupling": 3.960065
        },
        {
          "type": "WORK",
          "label": "40s@379w83rpm",
          "duration_secs": 40,
          "avg_power": 384,
          "max_power": 444,
          "avg_hr": 133,
          "max_hr": 142,
          "avg_cadence": 93.55,
          "zone": 6,
          "training_load": 1.3460323,
          "decoupling": 1.1017513
        },
        {
          "type": "RECOVERY",
          "duration_secs": 597,
          "avg_power": 220,
          "max_power": 604,
          "avg_hr": 128,
          "max_hr": 143,
          "avg_cadence": 76.28141,
          "zone": 2,
          "training_load": 11.0133095,
          "decoupling": 3.136229
        },
        {
          "type": "WORK",
          "label": "40s@379w83rpm",
          "duration_secs": 38,
          "avg_power": 448,
          "max_power": 472,
          "avg_hr": 141,
          "max_hr": 147,
          "avg_cadence": 92.63158,
          "zone": 6,
          "training_load": 1.6664857,
          "decoupling": 2.6310947
        },
        {
          "type": "RECOVERY",
          "duration_secs": 3586,
          "avg_power": 191,
          "max_power": 743,
          "avg_hr": 119,
          "max_hr": 149,
          "avg_cadence": 65.71203,
          "zone": 2,
          "training_load": 23.436388
        },
        {
          "type": "WORK",
          "label": "12s@492w84rpm",
          "duration_secs": 12,
          "avg_power": 492,
          "max_power": 638,
          "avg_hr": 124,
          "max_hr": 128,
          "avg_cadence": 84.333336,
          "zone": 7,
          "training_load": 0.20748651,
          "decoupling": 29.790627
        },
        {
          "type": "RECOVERY",
          "duration_secs": 277,
          "avg_power": 220,
          "max_power": 673,
          "avg_hr": 129,
          "max_hr": 140,
          "avg_cadence": 71.6065,
          "zone": 2,
          "training_load": 5.357252,
          "decoupling": 7.775237
        }
      ]
    }
  ]
}